alumath_group20/__init__.py
alumath_group20/matrix.py
alumath_group20-0.1.0.dist-info/licenses/LICENSE
alumath_group20-0.1.0.dist-info/METADATA
alumath_group20-0.1.0.dist-info/WHEEL
alumath_group20-0.1.0.dist-info/top_level.txt
alumath_group20-0.1.0.dist-info/RECORD
