Metadata-Version: 2.4
Name: alumath_group20
Version: 0.1.0
Summary: A library for matrix operations by Group 20
Home-page: https://github.com/yourusername/alumath_group20
Author: Christian, Carine, Eva, Thierry
Author-email: ishimwechris765@gmail.com
Classifier: Programming Language :: Python :: 3
Classifier: License :: OSI Approved :: MIT License
Classifier: Operating System :: OS Independent
Requires-Python: >=3.6
License-File: LICENSE
Dynamic: author
Dynamic: author-email
Dynamic: classifier
Dynamic: description
Dynamic: description-content-type
Dynamic: home-page
Dynamic: license-file
Dynamic: requires-python
Dynamic: summary
